[
  {
    "catalog_type": "SLCItem",
    "persistentID": "http://adapt2.sis.pitt.edu/lti/launch?tool=dbqa&sub=arithmetic-expressions-3",
    "platform_name": "DBQA",
    "title": "Arithmetic-expressions query execution 3",
    "description": "Arithmetic-expressions query execution 3",
    "license": "MIT",
    "author": [
      "Kamil Akhuseyinoglu"
    ],
    "institution": [
      "University of Pittsburgh"
    ],
    "keywords": [],
    "features": [],
    "programming_language": [
      "SQL"
    ],
    "natural_language": [
      "en"
    ],
    "iframe_url": "http://adapt2.sis.pitt.edu/lti/launch?tool=dbqa&sub=arithmetic-expressions-3&usr=adl01&grp=adl01",
    "protocol": [
      "LTI 1.1"
    ],
    "protocol_url": [
      "http://adapt2.sis.pitt.edu/lti/launch?tool=dbqa&sub=arithmetic-expressions-3"
    ]
  },
  {
    "catalog_type": "SLCItem",
    "persistentID": "http://adapt2.sis.pitt.edu/lti/launch?tool=dbqa&sub=arithmetic-expressions-4",
    "platform_name": "DBQA",
    "title": "Arithmetic-expressions query execution 4",
    "description": "Arithmetic-expressions query execution 4",
    "license": "MIT",
    "author": [
      "Kamil Akhuseyinoglu"
    ],
    "institution": [
      "University of Pittsburgh"
    ],
    "keywords": [],
    "features": [],
    "programming_language": [
      "SQL"
    ],
    "natural_language": [
      "en"
    ],
    "iframe_url": "http://adapt2.sis.pitt.edu/lti/launch?tool=dbqa&sub=arithmetic-expressions-4&usr=adl01&grp=adl01",
    "protocol": [
      "LTI 1.1"
    ],
    "protocol_url": [
      "http://adapt2.sis.pitt.edu/lti/launch?tool=dbqa&sub=arithmetic-expressions-4"
    ]
  },
  {
    "catalog_type": "SLCItem",
    "persistentID": "http://adapt2.sis.pitt.edu/lti/launch?tool=dbqa&sub=group-by-having-3",
    "platform_name": "DBQA",
    "title": "Group-by-having query execution 3",
    "description": "Group-by-having query execution 3",
    "license": "MIT",
    "author": [
      "Kamil Akhuseyinoglu"
    ],
    "institution": [
      "University of Pittsburgh"
    ],
    "keywords": [],
    "features": [],
    "programming_language": [
      "SQL"
    ],
    "natural_language": [
      "en"
    ],
    "iframe_url": "http://adapt2.sis.pitt.edu/lti/launch?tool=dbqa&sub=group-by-having-3&usr=adl01&grp=adl01",
    "protocol": [
      "LTI 1.1"
    ],
    "protocol_url": [
      "http://adapt2.sis.pitt.edu/lti/launch?tool=dbqa&sub=group-by-having-3"
    ]
  },
  {
    "catalog_type": "SLCItem",
    "persistentID": "http://adapt2.sis.pitt.edu/lti/launch?tool=dbqa&sub=pattern-matching-2",
    "platform_name": "DBQA",
    "title": "Pattern-matching query execution 2",
    "description": "Pattern-matching query execution 2",
    "license": "MIT",
    "author": [
      "Kamil Akhuseyinoglu"
    ],
    "institution": [
      "University of Pittsburgh"
    ],
    "keywords": [],
    "features": [],
    "programming_language": [
      "SQL"
    ],
    "natural_language": [
      "en"
    ],
    "iframe_url": "http://adapt2.sis.pitt.edu/lti/launch?tool=dbqa&sub=pattern-matching-2&usr=adl01&grp=adl01",
    "protocol": [
      "LTI 1.1"
    ],
    "protocol_url": [
      "http://adapt2.sis.pitt.edu/lti/launch?tool=dbqa&sub=pattern-matching-2"
    ]
  },
  {
    "catalog_type": "SLCItem",
    "persistentID": "http://adapt2.sis.pitt.edu/lti/launch?tool=dbqa&sub=left-join-4",
    "platform_name": "DBQA",
    "title": "Left-join query execution 4",
    "description": "Left-join query execution 4",
    "license": "MIT",
    "author": [
      "Rully Hendrawan"
    ],
    "institution": [
      "University of Pittsburgh"
    ],
    "keywords": [],
    "features": [],
    "programming_language": [
      "SQL"
    ],
    "natural_language": [
      "en"
    ],
    "iframe_url": "http://adapt2.sis.pitt.edu/lti/launch?tool=dbqa&sub=left-join-4&usr=adl01&grp=adl01",
    "protocol": [
      "LTI 1.1"
    ],
    "protocol_url": [
      "http://adapt2.sis.pitt.edu/lti/launch?tool=dbqa&sub=left-join-4"
    ]
  },
  {
    "catalog_type": "SLCItem",
    "persistentID": "http://adapt2.sis.pitt.edu/lti/launch?tool=dbqa&sub=inner-join-4",
    "platform_name": "DBQA",
    "title": "Inner-join query execution 4",
    "description": "Inner-join query execution 4",
    "license": "MIT",
    "author": [
      "Rully Hendrawan"
    ],
    "institution": [
      "University of Pittsburgh"
    ],
    "keywords": [],
    "features": [],
    "programming_language": [
      "SQL"
    ],
    "natural_language": [
      "en"
    ],
    "iframe_url": "http://adapt2.sis.pitt.edu/lti/launch?tool=dbqa&sub=inner-join-4&usr=adl01&grp=adl01",
    "protocol": [
      "LTI 1.1"
    ],
    "protocol_url": [
      "http://adapt2.sis.pitt.edu/lti/launch?tool=dbqa&sub=inner-join-4"
    ]
  },
  {
    "catalog_type": "SLCItem",
    "persistentID": "http://adapt2.sis.pitt.edu/lti/launch?tool=dbqa&sub=subqueries-1",
    "platform_name": "DBQA",
    "title": "Subqueries query execution 1",
    "description": "Subqueries query execution 1",
    "license": "MIT",
    "author": [
      "Kamil Akhuseyinoglu"
    ],
    "institution": [
      "University of Pittsburgh"
    ],
    "keywords": [],
    "features": [],
    "programming_language": [
      "SQL"
    ],
    "natural_language": [
      "en"
    ],
    "iframe_url": "http://adapt2.sis.pitt.edu/lti/launch?tool=dbqa&sub=subqueries-1&usr=adl01&grp=adl01",
    "protocol": [
      "LTI 1.1"
    ],
    "protocol_url": [
      "http://adapt2.sis.pitt.edu/lti/launch?tool=dbqa&sub=subqueries-1"
    ]
  },
  {
    "catalog_type": "SLCItem",
    "persistentID": "http://adapt2.sis.pitt.edu/lti/launch?tool=dbqa&sub=aggregate-functions-3",
    "platform_name": "DBQA",
    "title": "Aggregate-functions query execution 3",
    "description": "Aggregate-functions query execution 3",
    "license": "MIT",
    "author": [
      "Kamil Akhuseyinoglu"
    ],
    "institution": [
      "University of Pittsburgh"
    ],
    "keywords": [],
    "features": [],
    "programming_language": [
      "SQL"
    ],
    "natural_language": [
      "en"
    ],
    "iframe_url": "http://adapt2.sis.pitt.edu/lti/launch?tool=dbqa&sub=aggregate-functions-3&usr=adl01&grp=adl01",
    "protocol": [
      "LTI 1.1"
    ],
    "protocol_url": [
      "http://adapt2.sis.pitt.edu/lti/launch?tool=dbqa&sub=aggregate-functions-3"
    ]
  },
  {
    "catalog_type": "SLCItem",
    "persistentID": "http://adapt2.sis.pitt.edu/lti/launch?tool=dbqa&sub=join-4",
    "platform_name": "DBQA",
    "title": "Multiple-table-queries execution 4",
    "description": "Multiple-table-queries execution 4",
    "license": "MIT",
    "author": [
      "Kamil Akhuseyinoglu"
    ],
    "institution": [
      "University of Pittsburgh"
    ],
    "keywords": [],
    "features": [],
    "programming_language": [
      "SQL"
    ],
    "natural_language": [
      "en"
    ],
    "iframe_url": "http://adapt2.sis.pitt.edu/lti/launch?tool=dbqa&sub=join-4&usr=adl01&grp=adl01",
    "protocol": [
      "LTI 1.1"
    ],
    "protocol_url": [
      "http://adapt2.sis.pitt.edu/lti/launch?tool=dbqa&sub=join-4"
    ]
  },
  {
    "catalog_type": "SLCItem",
    "persistentID": "http://adapt2.sis.pitt.edu/lti/launch?tool=dbqa&sub=multiple-table-queries-1",
    "platform_name": "DBQA",
    "title": "Join query execution 1",
    "description": "Join query execution 1",
    "license": "MIT",
    "author": [
      "Kamil Akhuseyinoglu"
    ],
    "institution": [
      "University of Pittsburgh"
    ],
    "keywords": [],
    "features": [],
    "programming_language": [
      "SQL"
    ],
    "natural_language": [
      "en"
    ],
    "iframe_url": "http://adapt2.sis.pitt.edu/lti/launch?tool=dbqa&sub=multiple-table-queries-1&usr=adl01&grp=adl01",
    "protocol": [
      "LTI 1.1"
    ],
    "protocol_url": [
      "http://adapt2.sis.pitt.edu/lti/launch?tool=dbqa&sub=multiple-table-queries-1"
    ]
  },
  {
    "catalog_type": "SLCItem",
    "persistentID": "http://adapt2.sis.pitt.edu/lti/launch?tool=dbqa&sub=order-by-1",
    "platform_name": "DBQA",
    "title": "Order-by query execution 1",
    "description": "Order-by query execution 1",
    "license": "MIT",
    "author": [
      "Kamil Akhuseyinoglu"
    ],
    "institution": [
      "University of Pittsburgh"
    ],
    "keywords": [],
    "features": [],
    "programming_language": [
      "SQL"
    ],
    "natural_language": [
      "en"
    ],
    "iframe_url": "http://adapt2.sis.pitt.edu/lti/launch?tool=dbqa&sub=order-by-1&usr=adl01&grp=adl01",
    "protocol": [
      "LTI 1.1"
    ],
    "protocol_url": [
      "http://adapt2.sis.pitt.edu/lti/launch?tool=dbqa&sub=order-by-1"
    ]
  },
  {
    "catalog_type": "SLCItem",
    "persistentID": "http://adapt2.sis.pitt.edu/lti/launch?tool=dbqa&sub=subqueries-2",
    "platform_name": "DBQA",
    "title": "Subqueries query execution 2",
    "description": "Subqueries query execution 2",
    "license": "MIT",
    "author": [
      "Kamil Akhuseyinoglu"
    ],
    "institution": [
      "University of Pittsburgh"
    ],
    "keywords": [],
    "features": [],
    "programming_language": [
      "SQL"
    ],
    "natural_language": [
      "en"
    ],
    "iframe_url": "http://adapt2.sis.pitt.edu/lti/launch?tool=dbqa&sub=subqueries-2&usr=adl01&grp=adl01",
    "protocol": [
      "LTI 1.1"
    ],
    "protocol_url": [
      "http://adapt2.sis.pitt.edu/lti/launch?tool=dbqa&sub=subqueries-2"
    ]
  },
  {
    "catalog_type": "SLCItem",
    "persistentID": "http://adapt2.sis.pitt.edu/lti/launch?tool=dbqa&sub=select-from-where-1",
    "platform_name": "DBQA",
    "title": "Select-from-where query execution 1",
    "description": "Select-from-where query execution 1",
    "license": "MIT",
    "author": [
      "Kamil Akhuseyinoglu"
    ],
    "institution": [
      "University of Pittsburgh"
    ],
    "keywords": [],
    "features": [],
    "programming_language": [
      "SQL"
    ],
    "natural_language": [
      "en"
    ],
    "iframe_url": "http://adapt2.sis.pitt.edu/lti/launch?tool=dbqa&sub=select-from-where-1&usr=adl01&grp=adl01",
    "protocol": [
      "LTI 1.1"
    ],
    "protocol_url": [
      "http://adapt2.sis.pitt.edu/lti/launch?tool=dbqa&sub=select-from-where-1"
    ]
  },
  {
    "catalog_type": "SLCItem",
    "persistentID": "http://adapt2.sis.pitt.edu/lti/launch?tool=dbqa&sub=inner-join-2",
    "platform_name": "DBQA",
    "title": "Inner-join query execution 2",
    "description": "Inner-join query execution 2",
    "license": "MIT",
    "author": [
      "Rully Hendrawan"
    ],
    "institution": [
      "University of Pittsburgh"
    ],
    "keywords": [],
    "features": [],
    "programming_language": [
      "SQL"
    ],
    "natural_language": [
      "en"
    ],
    "iframe_url": "http://adapt2.sis.pitt.edu/lti/launch?tool=dbqa&sub=inner-join-2&usr=adl01&grp=adl01",
    "protocol": [
      "LTI 1.1"
    ],
    "protocol_url": [
      "http://adapt2.sis.pitt.edu/lti/launch?tool=dbqa&sub=inner-join-2"
    ]
  },
  {
    "catalog_type": "SLCItem",
    "persistentID": "http://adapt2.sis.pitt.edu/lti/launch?tool=dbqa&sub=join-2",
    "platform_name": "DBQA",
    "title": "Multiple-table-queries execution 2",
    "description": "Multiple-table-queries execution 2",
    "license": "MIT",
    "author": [
      "Kamil Akhuseyinoglu"
    ],
    "institution": [
      "University of Pittsburgh"
    ],
    "keywords": [],
    "features": [],
    "programming_language": [
      "SQL"
    ],
    "natural_language": [
      "en"
    ],
    "iframe_url": "http://adapt2.sis.pitt.edu/lti/launch?tool=dbqa&sub=join-2&usr=adl01&grp=adl01",
    "protocol": [
      "LTI 1.1"
    ],
    "protocol_url": [
      "http://adapt2.sis.pitt.edu/lti/launch?tool=dbqa&sub=join-2"
    ]
  },
  {
    "catalog_type": "SLCItem",
    "persistentID": "http://adapt2.sis.pitt.edu/lti/launch?tool=dbqa&sub=multiple-table-queries-2",
    "platform_name": "DBQA",
    "title": "Join query execution 2",
    "description": "Join query execution 2",
    "license": "MIT",
    "author": [
      "Kamil Akhuseyinoglu"
    ],
    "institution": [
      "University of Pittsburgh"
    ],
    "keywords": [],
    "features": [],
    "programming_language": [
      "SQL"
    ],
    "natural_language": [
      "en"
    ],
    "iframe_url": "http://adapt2.sis.pitt.edu/lti/launch?tool=dbqa&sub=multiple-table-queries-2&usr=adl01&grp=adl01",
    "protocol": [
      "LTI 1.1"
    ],
    "protocol_url": [
      "http://adapt2.sis.pitt.edu/lti/launch?tool=dbqa&sub=multiple-table-queries-2"
    ]
  },
  {
    "catalog_type": "SLCItem",
    "persistentID": "http://adapt2.sis.pitt.edu/lti/launch?tool=dbqa&sub=group-by-having-1",
    "platform_name": "DBQA",
    "title": "Group-by-having query execution 1",
    "description": "Group-by-having query execution 1",
    "license": "MIT",
    "author": [
      "Kamil Akhuseyinoglu"
    ],
    "institution": [
      "University of Pittsburgh"
    ],
    "keywords": [],
    "features": [],
    "programming_language": [
      "SQL"
    ],
    "natural_language": [
      "en"
    ],
    "iframe_url": "http://adapt2.sis.pitt.edu/lti/launch?tool=dbqa&sub=group-by-having-1&usr=adl01&grp=adl01",
    "protocol": [
      "LTI 1.1"
    ],
    "protocol_url": [
      "http://adapt2.sis.pitt.edu/lti/launch?tool=dbqa&sub=group-by-having-1"
    ]
  },
  {
    "catalog_type": "SLCItem",
    "persistentID": "http://adapt2.sis.pitt.edu/lti/launch?tool=dbqa&sub=order-by-4",
    "platform_name": "DBQA",
    "title": "Order-by query execution 4",
    "description": "Order-by query execution 4",
    "license": "MIT",
    "author": [
      "Kamil Akhuseyinoglu"
    ],
    "institution": [
      "University of Pittsburgh"
    ],
    "keywords": [],
    "features": [],
    "programming_language": [
      "SQL"
    ],
    "natural_language": [
      "en"
    ],
    "iframe_url": "http://adapt2.sis.pitt.edu/lti/launch?tool=dbqa&sub=order-by-4&usr=adl01&grp=adl01",
    "protocol": [
      "LTI 1.1"
    ],
    "protocol_url": [
      "http://adapt2.sis.pitt.edu/lti/launch?tool=dbqa&sub=order-by-4"
    ]
  },
  {
    "catalog_type": "SLCItem",
    "persistentID": "http://adapt2.sis.pitt.edu/lti/launch?tool=dbqa&sub=aggregate-functions-2",
    "platform_name": "DBQA",
    "title": "Aggregate-functions query execution 2",
    "description": "Aggregate-functions query execution 2",
    "license": "MIT",
    "author": [
      "Kamil Akhuseyinoglu"
    ],
    "institution": [
      "University of Pittsburgh"
    ],
    "keywords": [],
    "features": [],
    "programming_language": [
      "SQL"
    ],
    "natural_language": [
      "en"
    ],
    "iframe_url": "http://adapt2.sis.pitt.edu/lti/launch?tool=dbqa&sub=aggregate-functions-2&usr=adl01&grp=adl01",
    "protocol": [
      "LTI 1.1"
    ],
    "protocol_url": [
      "http://adapt2.sis.pitt.edu/lti/launch?tool=dbqa&sub=aggregate-functions-2"
    ]
  },
  {
    "catalog_type": "SLCItem",
    "persistentID": "http://adapt2.sis.pitt.edu/lti/launch?tool=dbqa&sub=inner-join-3",
    "platform_name": "DBQA",
    "title": "Inner-join query execution 3",
    "description": "Inner-join query execution 3",
    "license": "MIT",
    "author": [
      "Rully Hendrawan"
    ],
    "institution": [
      "University of Pittsburgh"
    ],
    "keywords": [],
    "features": [],
    "programming_language": [
      "SQL"
    ],
    "natural_language": [
      "en"
    ],
    "iframe_url": "http://adapt2.sis.pitt.edu/lti/launch?tool=dbqa&sub=inner-join-3&usr=adl01&grp=adl01",
    "protocol": [
      "LTI 1.1"
    ],
    "protocol_url": [
      "http://adapt2.sis.pitt.edu/lti/launch?tool=dbqa&sub=inner-join-3"
    ]
  },
  {
    "catalog_type": "SLCItem",
    "persistentID": "http://adapt2.sis.pitt.edu/lti/launch?tool=dbqa&sub=select-from-where-2",
    "platform_name": "DBQA",
    "title": "Select-from-where query execution 2",
    "description": "Select-from-where query execution 2",
    "license": "MIT",
    "author": [
      "Kamil Akhuseyinoglu"
    ],
    "institution": [
      "University of Pittsburgh"
    ],
    "keywords": [],
    "features": [],
    "programming_language": [
      "SQL"
    ],
    "natural_language": [
      "en"
    ],
    "iframe_url": "http://adapt2.sis.pitt.edu/lti/launch?tool=dbqa&sub=select-from-where-2&usr=adl01&grp=adl01",
    "protocol": [
      "LTI 1.1"
    ],
    "protocol_url": [
      "http://adapt2.sis.pitt.edu/lti/launch?tool=dbqa&sub=select-from-where-2"
    ]
  },
  {
    "catalog_type": "SLCItem",
    "persistentID": "http://adapt2.sis.pitt.edu/lti/launch?tool=dbqa&sub=arithmetic-expressions-5",
    "platform_name": "DBQA",
    "title": "Arithmetic-expressions query execution 5",
    "description": "Arithmetic-expressions query execution 5",
    "license": "MIT",
    "author": [
      "Kamil Akhuseyinoglu"
    ],
    "institution": [
      "University of Pittsburgh"
    ],
    "keywords": [],
    "features": [],
    "programming_language": [
      "SQL"
    ],
    "natural_language": [
      "en"
    ],
    "iframe_url": "http://adapt2.sis.pitt.edu/lti/launch?tool=dbqa&sub=arithmetic-expressions-5&usr=adl01&grp=adl01",
    "protocol": [
      "LTI 1.1"
    ],
    "protocol_url": [
      "http://adapt2.sis.pitt.edu/lti/launch?tool=dbqa&sub=arithmetic-expressions-5"
    ]
  },
  {
    "catalog_type": "SLCItem",
    "persistentID": "http://adapt2.sis.pitt.edu/lti/launch?tool=dbqa&sub=group-by-having-4",
    "platform_name": "DBQA",
    "title": "Group-by-having query execution 4",
    "description": "Group-by-having query execution 4",
    "license": "MIT",
    "author": [
      "Kamil Akhuseyinoglu"
    ],
    "institution": [
      "University of Pittsburgh"
    ],
    "keywords": [],
    "features": [],
    "programming_language": [
      "SQL"
    ],
    "natural_language": [
      "en"
    ],
    "iframe_url": "http://adapt2.sis.pitt.edu/lti/launch?tool=dbqa&sub=group-by-having-4&usr=adl01&grp=adl01",
    "protocol": [
      "LTI 1.1"
    ],
    "protocol_url": [
      "http://adapt2.sis.pitt.edu/lti/launch?tool=dbqa&sub=group-by-having-4"
    ]
  },
  {
    "catalog_type": "SLCItem",
    "persistentID": "http://adapt2.sis.pitt.edu/lti/launch?tool=dbqa&sub=pattern-matching-3",
    "platform_name": "DBQA",
    "title": "Pattern-matching query execution 3",
    "description": "Pattern-matching query execution 3",
    "license": "MIT",
    "author": [
      "Kamil Akhuseyinoglu"
    ],
    "institution": [
      "University of Pittsburgh"
    ],
    "keywords": [],
    "features": [],
    "programming_language": [
      "SQL"
    ],
    "natural_language": [
      "en"
    ],
    "iframe_url": "http://adapt2.sis.pitt.edu/lti/launch?tool=dbqa&sub=pattern-matching-3&usr=adl01&grp=adl01",
    "protocol": [
      "LTI 1.1"
    ],
    "protocol_url": [
      "http://adapt2.sis.pitt.edu/lti/launch?tool=dbqa&sub=pattern-matching-3"
    ]
  },
  {
    "catalog_type": "SLCItem",
    "persistentID": "http://adapt2.sis.pitt.edu/lti/launch?tool=dbqa&sub=order-by-3",
    "platform_name": "DBQA",
    "title": "Order-by query execution 3",
    "description": "Order-by query execution 3",
    "license": "MIT",
    "author": [
      "Kamil Akhuseyinoglu"
    ],
    "institution": [
      "University of Pittsburgh"
    ],
    "keywords": [],
    "features": [],
    "programming_language": [
      "SQL"
    ],
    "natural_language": [
      "en"
    ],
    "iframe_url": "http://adapt2.sis.pitt.edu/lti/launch?tool=dbqa&sub=order-by-3&usr=adl01&grp=adl01",
    "protocol": [
      "LTI 1.1"
    ],
    "protocol_url": [
      "http://adapt2.sis.pitt.edu/lti/launch?tool=dbqa&sub=order-by-3"
    ]
  },
  {
    "catalog_type": "SLCItem",
    "persistentID": "http://adapt2.sis.pitt.edu/lti/launch?tool=dbqa&sub=aggregate-functions-1",
    "platform_name": "DBQA",
    "title": "Aggregate-functions query execution 1",
    "description": "Aggregate-functions query execution 1",
    "license": "MIT",
    "author": [
      "Kamil Akhuseyinoglu"
    ],
    "institution": [
      "University of Pittsburgh"
    ],
    "keywords": [],
    "features": [],
    "programming_language": [
      "SQL"
    ],
    "natural_language": [
      "en"
    ],
    "iframe_url": "http://adapt2.sis.pitt.edu/lti/launch?tool=dbqa&sub=aggregate-functions-1&usr=adl01&grp=adl01",
    "protocol": [
      "LTI 1.1"
    ],
    "protocol_url": [
      "http://adapt2.sis.pitt.edu/lti/launch?tool=dbqa&sub=aggregate-functions-1"
    ]
  },
  {
    "catalog_type": "SLCItem",
    "persistentID": "http://adapt2.sis.pitt.edu/lti/launch?tool=dbqa&sub=aggregate-functions-4",
    "platform_name": "DBQA",
    "title": "Aggregate-functions query execution 4",
    "description": "Aggregate-functions query execution 4",
    "license": "MIT",
    "author": [
      "Kamil Akhuseyinoglu"
    ],
    "institution": [
      "University of Pittsburgh"
    ],
    "keywords": [],
    "features": [],
    "programming_language": [
      "SQL"
    ],
    "natural_language": [
      "en"
    ],
    "iframe_url": "http://adapt2.sis.pitt.edu/lti/launch?tool=dbqa&sub=aggregate-functions-4&usr=adl01&grp=adl01",
    "protocol": [
      "LTI 1.1"
    ],
    "protocol_url": [
      "http://adapt2.sis.pitt.edu/lti/launch?tool=dbqa&sub=aggregate-functions-4"
    ]
  },
  {
    "catalog_type": "SLCItem",
    "persistentID": "http://adapt2.sis.pitt.edu/lti/launch?tool=dbqa&sub=select-from-where-4",
    "platform_name": "DBQA",
    "title": "Select-from-where query execution 4",
    "description": "Select-from-where query execution 4",
    "license": "MIT",
    "author": [
      "Kamil Akhuseyinoglu"
    ],
    "institution": [
      "University of Pittsburgh"
    ],
    "keywords": [],
    "features": [],
    "programming_language": [
      "SQL"
    ],
    "natural_language": [
      "en"
    ],
    "iframe_url": "http://adapt2.sis.pitt.edu/lti/launch?tool=dbqa&sub=select-from-where-4&usr=adl01&grp=adl01",
    "protocol": [
      "LTI 1.1"
    ],
    "protocol_url": [
      "http://adapt2.sis.pitt.edu/lti/launch?tool=dbqa&sub=select-from-where-4"
    ]
  },
  {
    "catalog_type": "SLCItem",
    "persistentID": "http://adapt2.sis.pitt.edu/lti/launch?tool=dbqa&sub=left-join-2",
    "platform_name": "DBQA",
    "title": "Left-join query execution 2",
    "description": "Left-join query execution 2",
    "license": "MIT",
    "author": [
      "Rully Hendrawan"
    ],
    "institution": [
      "University of Pittsburgh"
    ],
    "keywords": [],
    "features": [],
    "programming_language": [
      "SQL"
    ],
    "natural_language": [
      "en"
    ],
    "iframe_url": "http://adapt2.sis.pitt.edu/lti/launch?tool=dbqa&sub=left-join-2&usr=adl01&grp=adl01",
    "protocol": [
      "LTI 1.1"
    ],
    "protocol_url": [
      "http://adapt2.sis.pitt.edu/lti/launch?tool=dbqa&sub=left-join-2"
    ]
  },
  {
    "catalog_type": "SLCItem",
    "persistentID": "http://adapt2.sis.pitt.edu/lti/launch?tool=dbqa&sub=select-from-3",
    "platform_name": "DBQA",
    "title": "Select-from query execution 3",
    "description": "Select-from query execution 3",
    "license": "MIT",
    "author": [
      "Kamil Akhuseyinoglu"
    ],
    "institution": [
      "University of Pittsburgh"
    ],
    "keywords": [],
    "features": [],
    "programming_language": [
      "SQL"
    ],
    "natural_language": [
      "en"
    ],
    "iframe_url": "http://adapt2.sis.pitt.edu/lti/launch?tool=dbqa&sub=select-from-3&usr=adl01&grp=adl01",
    "protocol": [
      "LTI 1.1"
    ],
    "protocol_url": [
      "http://adapt2.sis.pitt.edu/lti/launch?tool=dbqa&sub=select-from-3"
    ]
  },
  {
    "catalog_type": "SLCItem",
    "persistentID": "http://adapt2.sis.pitt.edu/lti/launch?tool=dbqa&sub=arithmetic-expressions-6",
    "platform_name": "DBQA",
    "title": "Arithmetic-expressions query execution 6",
    "description": "Arithmetic-expressions query execution 6",
    "license": "MIT",
    "author": [
      "Kamil Akhuseyinoglu"
    ],
    "institution": [
      "University of Pittsburgh"
    ],
    "keywords": [],
    "features": [],
    "programming_language": [
      "SQL"
    ],
    "natural_language": [
      "en"
    ],
    "iframe_url": "http://adapt2.sis.pitt.edu/lti/launch?tool=dbqa&sub=arithmetic-expressions-6&usr=adl01&grp=adl01",
    "protocol": [
      "LTI 1.1"
    ],
    "protocol_url": [
      "http://adapt2.sis.pitt.edu/lti/launch?tool=dbqa&sub=arithmetic-expressions-6"
    ]
  },
  {
    "catalog_type": "SLCItem",
    "persistentID": "http://adapt2.sis.pitt.edu/lti/launch?tool=dbqa&sub=order-by-2",
    "platform_name": "DBQA",
    "title": "Order-by query execution 2",
    "description": "Order-by query execution 2",
    "license": "MIT",
    "author": [
      "Kamil Akhuseyinoglu"
    ],
    "institution": [
      "University of Pittsburgh"
    ],
    "keywords": [],
    "features": [],
    "programming_language": [
      "SQL"
    ],
    "natural_language": [
      "en"
    ],
    "iframe_url": "http://adapt2.sis.pitt.edu/lti/launch?tool=dbqa&sub=order-by-2&usr=adl01&grp=adl01",
    "protocol": [
      "LTI 1.1"
    ],
    "protocol_url": [
      "http://adapt2.sis.pitt.edu/lti/launch?tool=dbqa&sub=order-by-2"
    ]
  },
  {
    "catalog_type": "SLCItem",
    "persistentID": "http://adapt2.sis.pitt.edu/lti/launch?tool=dbqa&sub=subqueries-4",
    "platform_name": "DBQA",
    "title": "Subqueries query execution 4",
    "description": "Subqueries query execution 4",
    "license": "MIT",
    "author": [
      "Kamil Akhuseyinoglu"
    ],
    "institution": [
      "University of Pittsburgh"
    ],
    "keywords": [],
    "features": [],
    "programming_language": [
      "SQL"
    ],
    "natural_language": [
      "en"
    ],
    "iframe_url": "http://adapt2.sis.pitt.edu/lti/launch?tool=dbqa&sub=subqueries-4&usr=adl01&grp=adl01",
    "protocol": [
      "LTI 1.1"
    ],
    "protocol_url": [
      "http://adapt2.sis.pitt.edu/lti/launch?tool=dbqa&sub=subqueries-4"
    ]
  },
  {
    "catalog_type": "SLCItem",
    "persistentID": "http://adapt2.sis.pitt.edu/lti/launch?tool=dbqa&sub=multiple-table-queries-3",
    "platform_name": "DBQA",
    "title": "Join query execution 3",
    "description": "Join query execution 3",
    "license": "MIT",
    "author": [
      "Kamil Akhuseyinoglu"
    ],
    "institution": [
      "University of Pittsburgh"
    ],
    "keywords": [],
    "features": [],
    "programming_language": [
      "SQL"
    ],
    "natural_language": [
      "en"
    ],
    "iframe_url": "http://adapt2.sis.pitt.edu/lti/launch?tool=dbqa&sub=multiple-table-queries-3&usr=adl01&grp=adl01",
    "protocol": [
      "LTI 1.1"
    ],
    "protocol_url": [
      "http://adapt2.sis.pitt.edu/lti/launch?tool=dbqa&sub=multiple-table-queries-3"
    ]
  },
  {
    "catalog_type": "SLCItem",
    "persistentID": "http://adapt2.sis.pitt.edu/lti/launch?tool=dbqa&sub=select-from-4",
    "platform_name": "DBQA",
    "title": "Select-from query execution 4",
    "description": "Select-from query execution 4",
    "license": "MIT",
    "author": [
      "Kamil Akhuseyinoglu"
    ],
    "institution": [
      "University of Pittsburgh"
    ],
    "keywords": [],
    "features": [],
    "programming_language": [
      "SQL"
    ],
    "natural_language": [
      "en"
    ],
    "iframe_url": "http://adapt2.sis.pitt.edu/lti/launch?tool=dbqa&sub=select-from-4&usr=adl01&grp=adl01",
    "protocol": [
      "LTI 1.1"
    ],
    "protocol_url": [
      "http://adapt2.sis.pitt.edu/lti/launch?tool=dbqa&sub=select-from-4"
    ]
  },
  {
    "catalog_type": "SLCItem",
    "persistentID": "http://adapt2.sis.pitt.edu/lti/launch?tool=dbqa&sub=group-by-having-2",
    "platform_name": "DBQA",
    "title": "Group-by-having query execution 2",
    "description": "Group-by-having query execution 2",
    "license": "MIT",
    "author": [
      "Kamil Akhuseyinoglu"
    ],
    "institution": [
      "University of Pittsburgh"
    ],
    "keywords": [],
    "features": [],
    "programming_language": [
      "SQL"
    ],
    "natural_language": [
      "en"
    ],
    "iframe_url": "http://adapt2.sis.pitt.edu/lti/launch?tool=dbqa&sub=group-by-having-2&usr=adl01&grp=adl01",
    "protocol": [
      "LTI 1.1"
    ],
    "protocol_url": [
      "http://adapt2.sis.pitt.edu/lti/launch?tool=dbqa&sub=group-by-having-2"
    ]
  },
  {
    "catalog_type": "SLCItem",
    "persistentID": "http://adapt2.sis.pitt.edu/lti/launch?tool=dbqa&sub=select-from-where-3",
    "platform_name": "DBQA",
    "title": "Select-from-where query execution 3",
    "description": "Select-from-where query execution 3",
    "license": "MIT",
    "author": [
      "Kamil Akhuseyinoglu"
    ],
    "institution": [
      "University of Pittsburgh"
    ],
    "keywords": [],
    "features": [],
    "programming_language": [
      "SQL"
    ],
    "natural_language": [
      "en"
    ],
    "iframe_url": "http://adapt2.sis.pitt.edu/lti/launch?tool=dbqa&sub=select-from-where-3&usr=adl01&grp=adl01",
    "protocol": [
      "LTI 1.1"
    ],
    "protocol_url": [
      "http://adapt2.sis.pitt.edu/lti/launch?tool=dbqa&sub=select-from-where-3"
    ]
  },
  {
    "catalog_type": "SLCItem",
    "persistentID": "http://adapt2.sis.pitt.edu/lti/launch?tool=dbqa&sub=left-join-1",
    "platform_name": "DBQA",
    "title": "Left-join query execution 1",
    "description": "Left-join query execution 1",
    "license": "MIT",
    "author": [
      "Rully Hendrawan"
    ],
    "institution": [
      "University of Pittsburgh"
    ],
    "keywords": [],
    "features": [],
    "programming_language": [
      "SQL"
    ],
    "natural_language": [
      "en"
    ],
    "iframe_url": "http://adapt2.sis.pitt.edu/lti/launch?tool=dbqa&sub=left-join-1&usr=adl01&grp=adl01",
    "protocol": [
      "LTI 1.1"
    ],
    "protocol_url": [
      "http://adapt2.sis.pitt.edu/lti/launch?tool=dbqa&sub=left-join-1"
    ]
  },
  {
    "catalog_type": "SLCItem",
    "persistentID": "http://adapt2.sis.pitt.edu/lti/launch?tool=dbqa&sub=inner-join-1",
    "platform_name": "DBQA",
    "title": "Inner-join query execution 1",
    "description": "Inner-join query execution 1",
    "license": "MIT",
    "author": [
      "Rully Hendrawan"
    ],
    "institution": [
      "University of Pittsburgh"
    ],
    "keywords": [],
    "features": [],
    "programming_language": [
      "SQL"
    ],
    "natural_language": [
      "en"
    ],
    "iframe_url": "http://adapt2.sis.pitt.edu/lti/launch?tool=dbqa&sub=inner-join-1&usr=adl01&grp=adl01",
    "protocol": [
      "LTI 1.1"
    ],
    "protocol_url": [
      "http://adapt2.sis.pitt.edu/lti/launch?tool=dbqa&sub=inner-join-1"
    ]
  },
  {
    "catalog_type": "SLCItem",
    "persistentID": "http://adapt2.sis.pitt.edu/lti/launch?tool=dbqa&sub=arithmetic-expressions-1",
    "platform_name": "DBQA",
    "title": "Arithmetic-expressions query execution 1",
    "description": "Arithmetic-expressions query execution 1",
    "license": "MIT",
    "author": [
      "Kamil Akhuseyinoglu"
    ],
    "institution": [
      "University of Pittsburgh"
    ],
    "keywords": [],
    "features": [],
    "programming_language": [
      "SQL"
    ],
    "natural_language": [
      "en"
    ],
    "iframe_url": "http://adapt2.sis.pitt.edu/lti/launch?tool=dbqa&sub=arithmetic-expressions-1&usr=adl01&grp=adl01",
    "protocol": [
      "LTI 1.1"
    ],
    "protocol_url": [
      "http://adapt2.sis.pitt.edu/lti/launch?tool=dbqa&sub=arithmetic-expressions-1"
    ]
  },
  {
    "catalog_type": "SLCItem",
    "persistentID": "http://adapt2.sis.pitt.edu/lti/launch?tool=dbqa&sub=arithmetic-expressions-2",
    "platform_name": "DBQA",
    "title": "Arithmetic-expressions query execution 2",
    "description": "Arithmetic-expressions query execution 2",
    "license": "MIT",
    "author": [
      "Kamil Akhuseyinoglu"
    ],
    "institution": [
      "University of Pittsburgh"
    ],
    "keywords": [],
    "features": [],
    "programming_language": [
      "SQL"
    ],
    "natural_language": [
      "en"
    ],
    "iframe_url": "http://adapt2.sis.pitt.edu/lti/launch?tool=dbqa&sub=arithmetic-expressions-2&usr=adl01&grp=adl01",
    "protocol": [
      "LTI 1.1"
    ],
    "protocol_url": [
      "http://adapt2.sis.pitt.edu/lti/launch?tool=dbqa&sub=arithmetic-expressions-2"
    ]
  },
  {
    "catalog_type": "SLCItem",
    "persistentID": "http://adapt2.sis.pitt.edu/lti/launch?tool=dbqa&sub=left-join-3",
    "platform_name": "DBQA",
    "title": "Left-join query execution 3",
    "description": "Left-join query execution 3",
    "license": "MIT",
    "author": [
      "Rully Hendrawan"
    ],
    "institution": [
      "University of Pittsburgh"
    ],
    "keywords": [],
    "features": [],
    "programming_language": [
      "SQL"
    ],
    "natural_language": [
      "en"
    ],
    "iframe_url": "http://adapt2.sis.pitt.edu/lti/launch?tool=dbqa&sub=left-join-3&usr=adl01&grp=adl01",
    "protocol": [
      "LTI 1.1"
    ],
    "protocol_url": [
      "http://adapt2.sis.pitt.edu/lti/launch?tool=dbqa&sub=left-join-3"
    ]
  },
  {
    "catalog_type": "SLCItem",
    "persistentID": "http://adapt2.sis.pitt.edu/lti/launch?tool=dbqa&sub=subqueries-3",
    "platform_name": "DBQA",
    "title": "Subqueries query execution 3",
    "description": "Subqueries query execution 3",
    "license": "MIT",
    "author": [
      "Kamil Akhuseyinoglu"
    ],
    "institution": [
      "University of Pittsburgh"
    ],
    "keywords": [],
    "features": [],
    "programming_language": [
      "SQL"
    ],
    "natural_language": [
      "en"
    ],
    "iframe_url": "http://adapt2.sis.pitt.edu/lti/launch?tool=dbqa&sub=subqueries-3&usr=adl01&grp=adl01",
    "protocol": [
      "LTI 1.1"
    ],
    "protocol_url": [
      "http://adapt2.sis.pitt.edu/lti/launch?tool=dbqa&sub=subqueries-3"
    ]
  },
  {
    "catalog_type": "SLCItem",
    "persistentID": "http://adapt2.sis.pitt.edu/lti/launch?tool=dbqa&sub=pattern-matching-1",
    "platform_name": "DBQA",
    "title": "Pattern-matching query execution 1",
    "description": "Pattern-matching query execution 1",
    "license": "MIT",
    "author": [
      "Kamil Akhuseyinoglu"
    ],
    "institution": [
      "University of Pittsburgh"
    ],
    "keywords": [],
    "features": [],
    "programming_language": [
      "SQL"
    ],
    "natural_language": [
      "en"
    ],
    "iframe_url": "http://adapt2.sis.pitt.edu/lti/launch?tool=dbqa&sub=pattern-matching-1&usr=adl01&grp=adl01",
    "protocol": [
      "LTI 1.1"
    ],
    "protocol_url": [
      "http://adapt2.sis.pitt.edu/lti/launch?tool=dbqa&sub=pattern-matching-1"
    ]
  },
  {
    "catalog_type": "SLCItem",
    "persistentID": "http://adapt2.sis.pitt.edu/lti/launch?tool=dbqa&sub=multiple-table-queries-4",
    "platform_name": "DBQA",
    "title": "Join query execution 4",
    "description": "Join query execution 4",
    "license": "MIT",
    "author": [
      "Kamil Akhuseyinoglu"
    ],
    "institution": [
      "University of Pittsburgh"
    ],
    "keywords": [],
    "features": [],
    "programming_language": [
      "SQL"
    ],
    "natural_language": [
      "en"
    ],
    "iframe_url": "http://adapt2.sis.pitt.edu/lti/launch?tool=dbqa&sub=multiple-table-queries-4&usr=adl01&grp=adl01",
    "protocol": [
      "LTI 1.1"
    ],
    "protocol_url": [
      "http://adapt2.sis.pitt.edu/lti/launch?tool=dbqa&sub=multiple-table-queries-4"
    ]
  },
  {
    "catalog_type": "SLCItem",
    "persistentID": "http://adapt2.sis.pitt.edu/lti/launch?tool=dbqa&sub=join-1",
    "platform_name": "DBQA",
    "title": "Multiple-table-queries execution 1",
    "description": "Multiple-table-queries execution 1",
    "license": "MIT",
    "author": [
      "Kamil Akhuseyinoglu"
    ],
    "institution": [
      "University of Pittsburgh"
    ],
    "keywords": [],
    "features": [],
    "programming_language": [
      "SQL"
    ],
    "natural_language": [
      "en"
    ],
    "iframe_url": "http://adapt2.sis.pitt.edu/lti/launch?tool=dbqa&sub=join-1&usr=adl01&grp=adl01",
    "protocol": [
      "LTI 1.1"
    ],
    "protocol_url": [
      "http://adapt2.sis.pitt.edu/lti/launch?tool=dbqa&sub=join-1"
    ]
  },
  {
    "catalog_type": "SLCItem",
    "persistentID": "http://adapt2.sis.pitt.edu/lti/launch?tool=dbqa&sub=select-from-1",
    "platform_name": "DBQA",
    "title": "Select-from query execution 1",
    "description": "Select-from query execution 1",
    "license": "MIT",
    "author": [
      "Kamil Akhuseyinoglu"
    ],
    "institution": [
      "University of Pittsburgh"
    ],
    "keywords": [],
    "features": [],
    "programming_language": [
      "SQL"
    ],
    "natural_language": [
      "en"
    ],
    "iframe_url": "http://adapt2.sis.pitt.edu/lti/launch?tool=dbqa&sub=select-from-1&usr=adl01&grp=adl01",
    "protocol": [
      "LTI 1.1"
    ],
    "protocol_url": [
      "http://adapt2.sis.pitt.edu/lti/launch?tool=dbqa&sub=select-from-1"
    ]
  },
  {
    "catalog_type": "SLCItem",
    "persistentID": "http://adapt2.sis.pitt.edu/lti/launch?tool=dbqa&sub=join-3",
    "platform_name": "DBQA",
    "title": "Multiple-table-queries execution 3",
    "description": "Multiple-table-queries execution 3",
    "license": "MIT",
    "author": [
      "Kamil Akhuseyinoglu"
    ],
    "institution": [
      "University of Pittsburgh"
    ],
    "keywords": [],
    "features": [],
    "programming_language": [
      "SQL"
    ],
    "natural_language": [
      "en"
    ],
    "iframe_url": "http://adapt2.sis.pitt.edu/lti/launch?tool=dbqa&sub=join-3&usr=adl01&grp=adl01",
    "protocol": [
      "LTI 1.1"
    ],
    "protocol_url": [
      "http://adapt2.sis.pitt.edu/lti/launch?tool=dbqa&sub=join-3"
    ]
  },
  {
    "catalog_type": "SLCItem",
    "persistentID": "http://adapt2.sis.pitt.edu/lti/launch?tool=dbqa&sub=pattern-matching-4",
    "platform_name": "DBQA",
    "title": "Pattern-matching query execution 4",
    "description": "Pattern-matching query execution 4",
    "license": "MIT",
    "author": [
      "Kamil Akhuseyinoglu"
    ],
    "institution": [
      "University of Pittsburgh"
    ],
    "keywords": [],
    "features": [],
    "programming_language": [
      "SQL"
    ],
    "natural_language": [
      "en"
    ],
    "iframe_url": "http://adapt2.sis.pitt.edu/lti/launch?tool=dbqa&sub=pattern-matching-4&usr=adl01&grp=adl01",
    "protocol": [
      "LTI 1.1"
    ],
    "protocol_url": [
      "http://adapt2.sis.pitt.edu/lti/launch?tool=dbqa&sub=pattern-matching-4"
    ]
  },
  {
    "catalog_type": "SLCItem",
    "persistentID": "http://adapt2.sis.pitt.edu/lti/launch?tool=dbqa&sub=select-from-2",
    "platform_name": "DBQA",
    "title": "Select-from query execution 2",
    "description": "Select-from query execution 2",
    "license": "MIT",
    "author": [
      "Kamil Akhuseyinoglu"
    ],
    "institution": [
      "University of Pittsburgh"
    ],
    "keywords": [],
    "features": [],
    "programming_language": [
      "SQL"
    ],
    "natural_language": [
      "en"
    ],
    "iframe_url": "http://adapt2.sis.pitt.edu/lti/launch?tool=dbqa&sub=select-from-2&usr=adl01&grp=adl01",
    "protocol": [
      "LTI 1.1"
    ],
    "protocol_url": [
      "http://adapt2.sis.pitt.edu/lti/launch?tool=dbqa&sub=select-from-2"
    ]
  }
]